src/__init__.py
src/init.py
src/Linhuiba/__init__.py
src/Linhuiba/conn_mongo.py
guanwai_tools-1.0.4.dist-info/LICENSE
guanwai_tools-1.0.4.dist-info/METADATA
guanwai_tools-1.0.4.dist-info/WHEEL
guanwai_tools-1.0.4.dist-info/top_level.txt
guanwai_tools-1.0.4.dist-info/RECORD
